kikiutils_image/__init__.py
kikiutils_image/aio.py
kikiutils_image/sync.py
kikiutils_image/typehint.py
kiki_utils_image-1.0.9.dist-info/LICENSE.txt
kiki_utils_image-1.0.9.dist-info/METADATA
kiki_utils_image-1.0.9.dist-info/WHEEL
kiki_utils_image-1.0.9.dist-info/top_level.txt
kiki_utils_image-1.0.9.dist-info/zip-safe
kiki_utils_image-1.0.9.dist-info/RECORD
