Metadata-Version: 2.1
Name: kiki-utils-image
Version: 1.0.9
Summary: Utils image functions.
Author: kiki-kanri
Author-email: a470666@gmail.com
Keywords: Utils
Classifier: License :: Freely Distributable
Requires-Python: >=3.8
License-File: LICENSE.txt
Requires-Dist: kiki-utils
Requires-Dist: opencv-python
Requires-Dist: pillow
Requires-Dist: requests
